mastermind_tk/__init__.py
mastermind_tk/__main__.py
mastermind_tk/mastermind_tk.py
mastermind_tk/resources/icon-font.png
mastermind_tk/resources/icon.ico
mastermind_tk/resources/icon.png
mastermind_tk-1.1.4.dist-info/METADATA
mastermind_tk-1.1.4.dist-info/WHEEL
mastermind_tk-1.1.4.dist-info/entry_points.txt
mastermind_tk-1.1.4.dist-info/top_level.txt
mastermind_tk-1.1.4.dist-info/RECORD
