Metadata-Version: 2.4
Name: mastermind_tk
Version: 1.1.4
Summary: Jeu du mastermind en version graphique
Home-page: https://github.com/bouquet-cedric/module-python
Author: Bouquet Cédric
Author-email: cedric-bouquet-7@outlook.fr
Classifier: Programming Language :: Python :: 3
Requires: tkinter
Requires: pillow
Requires: functools
Requires: random
Requires: importlib
Requires: getpass
Requires-Python: >=3.0
Dynamic: author
Dynamic: author-email
Dynamic: classifier
Dynamic: home-page
Dynamic: requires
Dynamic: requires-python
Dynamic: summary
